openemr/__init__.py
openemr/client.py
openemr/patient.py
openemr-0.4.6.dist-info/licenses/LICENSE
openemr-0.4.6.dist-info/METADATA
openemr-0.4.6.dist-info/WHEEL
openemr-0.4.6.dist-info/top_level.txt
openemr-0.4.6.dist-info/RECORD
