Metadata-Version: 2.4
Name: openemr
Version: 0.4.6
Summary: An OpenEMR api connector
Home-page: https://gitlab.com/aapjeisbaas/openemr-python
Author: Stein van Broekhoven
Author-email: stein@aapjeisbaas.nl
Classifier: Programming Language :: Python :: 3
Classifier: License :: OSI Approved :: MIT License
Classifier: Operating System :: OS Independent
Requires-Python: >=3.6
License-File: LICENSE
Requires-Dist: requests
Dynamic: author
Dynamic: author-email
Dynamic: classifier
Dynamic: description
Dynamic: description-content-type
Dynamic: home-page
Dynamic: license-file
Dynamic: requires-dist
Dynamic: requires-python
Dynamic: summary
